{
    "fluentMethods": true,
    "relationships": [
        {
            "relationshipType": "many-to-one",
            "relationshipName": "producto",
            "otherEntityName": "producto",
            "otherEntityField": "id"
        },
        {
            "relationshipName": "entrega",
            "otherEntityName": "entrega",
            "relationshipType": "many-to-one",
            "otherEntityField": "id"
        }
    ],
    "fields": [
        {
            "fieldName": "cantidad",
            "fieldType": "Integer",
            "fieldValidateRules": [
                "required"
            ]
        }
    ],
    "changelogDate": "20180620020742",
    "entityTableName": "linea_entrega",
    "dto": "mapstruct",
    "pagination": "no",
    "service": "no",
    "jpaMetamodelFiltering": false
}